{
    "12a1563a-83f3-2e63-d0ed-43077b95e852": {
        "paletteKey": "FlexLayoutCol",
        "commentid": null,
        "designerReference": [
            {
                "_key": "componentLabel",
                "_value": "Column",
                "_type": "kv",
                "_attrDef": "p",
                "_useAsLabel": true
            },
            {
                "_key": "style",
                "_value": "",
                "_type": "kv",
                "_attrDef": "p"
            },
            {
                "_key": "class",
                "_value": "",
                "_type": "dav",
                "_attrDef": "p"
            },
            {
                "_key": "fxFlex",
                "_value": "",
                "_type": "kv",
                "_attrDef": "p"
            },
            {
                "_key": "fxLayoutGap",
                "_value": "",
                "_type": "kv",
                "_attrDef": "p"
            },
            {
                "_key": "wrap",
                "_value": "wrap",
                "_type": "a",
                "_attrDef": "p"
            },
            {
                "_key": "layoutAlign",
                "_value": "start",
                "_type": "a",
                "_attrDef": "p"
            },
            {
                "_key": "pLayoutAlign",
                "_value": "stretch",
                "_type": "a",
                "_attrDef": "p"
            },
            {
                "_key": "[fxShow]",
                "_value": "true",
                "_type": "kv",
                "_attrDef": "p"
            }
        ],
        "139f5212-65b8-e9f9-974e-6de8057172e9": {
            "paletteKey": "FlexLayoutCol",
            "parentEditorKey": "12a1563a-83f3-2e63-d0ed-43077b95e852",
            "commentid": null,
            "designerReference": [
                {
                    "_key": "componentLabel",
                    "_value": "Column",
                    "_type": "kv",
                    "_attrDef": "p",
                    "_useAsLabel": true
                },
                {
                    "_key": "style",
                    "_value": "",
                    "_type": "kv",
                    "_attrDef": "p"
                },
                {
                    "_key": "class",
                    "_value": "",
                    "_type": "dav",
                    "_attrDef": "p"
                },
                {
                    "_key": "fxFlex",
                    "_value": "",
                    "_type": "kv",
                    "_attrDef": "p"
                },
                {
                    "_key": "fxLayoutGap",
                    "_value": "",
                    "_type": "kv",
                    "_attrDef": "p"
                },
                {
                    "_key": "wrap",
                    "_value": "wrap",
                    "_type": "a",
                    "_attrDef": "p"
                },
                {
                    "_key": "layoutAlign",
                    "_value": "start",
                    "_type": "a",
                    "_attrDef": "p"
                },
                {
                    "_key": "pLayoutAlign",
                    "_value": "stretch",
                    "_type": "a",
                    "_attrDef": "p"
                },
                {
                    "_key": "[fxShow]",
                    "_value": "true",
                    "_type": "kv",
                    "_attrDef": "p"
                }
            ],
            "a4e6c246-d45b-69d8-a823-5a721f845f51": {
                "paletteKey": "Html5",
                "parentEditorKey": "139f5212-65b8-e9f9-974e-6de8057172e9",
                "isAdvancedComponent": true,
                "commentid": null,
                "designerReference": [
                    {
                        "_key": "style",
                        "_value": "",
                        "_type": "kv",
                        "_attrDef": "p"
                    },
                    {
                        "_key": "class",
                        "_value": [
                            "m-b-0"
                        ],
                        "_type": "dav",
                        "_attrDef": "p"
                    },
                    {
                        "_key": "htmlElement",
                        "_value": "p",
                        "_type": "dav",
                        "_attrDef": "p",
                        "_useAsLabel": true
                    },
                    {
                        "_key": "tagType",
                        "_value": "p",
                        "_type": "a",
                        "_attrDef": "p",
                        "_visibility": false
                    },
                    {
                        "_key": "name",
                        "_value": "",
                        "_type": "kv",
                        "_attrDef": "p",
                        "_visibility": false
                    },
                    {
                        "_key": "sandbox",
                        "_value": "",
                        "_type": "kv",
                        "_attrDef": "p",
                        "_visibility": false
                    },
                    {
                        "_key": "src",
                        "_value": "",
                        "_type": "kv",
                        "_attrDef": "p",
                        "_visibility": false
                    },
                    {
                        "_key": "srcdoc",
                        "_value": "",
                        "_type": "kv",
                        "_attrDef": "p",
                        "_visibility": false
                    },
                    {
                        "_key": "width",
                        "_value": "",
                        "_type": "kv",
                        "_attrDef": "p",
                        "_visibility": false
                    },
                    {
                        "_key": "[autoplay]",
                        "_value": "",
                        "_type": "kv",
                        "_attrDef": "p",
                        "_visibility": false
                    },
                    {
                        "_key": "[loop]",
                        "_value": "",
                        "_type": "kv",
                        "_attrDef": "p",
                        "_visibility": false
                    },
                    {
                        "_key": "data",
                        "_value": "",
                        "_type": "kv",
                        "_attrDef": "p",
                        "_visibility": false
                    },
                    {
                        "_key": "audioSource",
                        "_value": [],
                        "_type": "a",
                        "_attrDef": "p",
                        "_visibility": false
                    },
                    {
                        "_key": "videoSource",
                        "_value": [],
                        "_type": "a",
                        "_attrDef": "p",
                        "_visibility": false
                    },
                    {
                        "_key": "audioDatasource",
                        "_value": "",
                        "_type": "a",
                        "_attrDef": "p",
                        "_visibility": false
                    },
                    {
                        "_key": "audioSrc",
                        "_value": "",
                        "_type": "a",
                        "_attrDef": "p",
                        "_visibility": false
                    },
                    {
                        "_key": "audioType",
                        "_value": "",
                        "_type": "a",
                        "_attrDef": "p",
                        "_visibility": false
                    },
                    {
                        "_key": "videoDatasource",
                        "_value": "",
                        "_type": "a",
                        "_attrDef": "p",
                        "_visibility": false
                    },
                    {
                        "_key": "videoSrc",
                        "_value": "",
                        "_type": "a",
                        "_attrDef": "p",
                        "_visibility": false
                    },
                    {
                        "_key": "videoType",
                        "_value": "",
                        "_type": "a",
                        "_attrDef": "p",
                        "_visibility": false
                    },
                    {
                        "_key": "(audioplay)",
                        "_value": "",
                        "_type": "a",
                        "_attrDef": "p",
                        "_visibility": false
                    },
                    {
                        "_key": "(videoplay)",
                        "_value": "",
                        "_type": "a",
                        "_attrDef": "p",
                        "_visibility": false
                    },
                    {
                        "_key": "(audiopause)",
                        "_value": "",
                        "_type": "kv",
                        "_attrDef": "p",
                        "_visibility": false
                    },
                    {
                        "_key": "(videopause)",
                        "_value": "",
                        "_type": "kv",
                        "_attrDef": "p",
                        "_visibility": false
                    },
                    {
                        "_key": "(audioended)",
                        "_value": "",
                        "_type": "kv",
                        "_attrDef": "p",
                        "_visibility": false
                    },
                    {
                        "_key": "(videoended)",
                        "_value": "",
                        "_type": "kv",
                        "_attrDef": "p",
                        "_visibility": false
                    }
                ],
                "f6b8c76d-edb5-7637-adef-c405004fc101": {
                    "paletteKey": "html-editor",
                    "parentEditorKey": "a4e6c246-d45b-69d8-a823-5a721f845f51",
                    "isAdvancedChildComponent": true,
                    "commentid": null,
                    "designerReference": [
                        {
                            "_key": "style",
                            "_value": "",
                            "_type": "kv",
                            "_attrDef": "p"
                        },
                        {
                            "_key": "class",
                            "_value": "",
                            "_type": "dav",
                            "_attrDef": "p"
                        },
                        {
                            "_key": "html",
                            "_value": "<small class=\"padding-left\">Capitec Bank is an authorised financial services provider (FSP 46669) and registereed credit provider (NCRCP13).<br>Capitec Bank Limited Reg No:1980/003695/06</small>",
                            "_type": "a",
                            "_attrDef": "p"
                        }
                    ]
                }
            }
        }
    }
}
